[{"url":"https://cn.bing.com/th?id=OHR.BrockenSpecter_EN-US5247366251_UHD.jpg&pid=hp&w=3840&h=2160&rs=1&c=4","preview":"https://cn.bing.com/th?id=OHR.BrockenSpecter_EN-US5247366251_UHD.jpg&pid=hp&w=384&h=216&rs=1&c=4","large":"https://cn.bing.com/th?id=OHR.BrockenSpecter_EN-US5247366251_UHD.jpg&pid=hp&w=3840&h=2160&rs=1&c=4","medium":"https://cn.bing.com/th?id=OHR.BrockenSpecter_EN-US5247366251_UHD.jpg&w=1000","copyright":"Brocken spectre in Central Balkan National Park, Bulgaria (© Maya Karkalicheva/Getty Images)","date":"2022-10-27","title":"A ghost on the mountain","copyrightlink":"/search?q=brocken+spectre&form=hpcapt&filters=HpDate%3a%2220221026_0700%22"},{"url":"https://cn.bing.com/th?id=OHR.OrcusMouth_EN-US5010597701_UHD.jpg&pid=hp&w=3840&h=2160&rs=1&c=4","preview":"https://cn.bing.com/th?id=OHR.OrcusMouth_EN-US5010597701_UHD.jpg&pid=hp&w=384&h=216&rs=1&c=4","large":"https://cn.bing.com/th?id=OHR.OrcusMouth_EN-US5010597701_UHD.jpg&pid=hp&w=3840&h=2160&rs=1&c=4","medium":"https://cn.bing.com/th?id=OHR.OrcusMouth_EN-US5010597701_UHD.jpg&w=1000","copyright":"Orcus sculpture in the Gardens of Bomarzo in Bomarzo, Italy (© Scott Wilson/Alamy)","date":"2022-10-26","title":"Park of the Monsters","copyrightlink":"/search?q=gardens+of+bomarzo+park+of+the+monsters+history&FORM=hpcapt&filters=HpDate%3a%2220221025_0700%22"},{"url":"https://cn.bing.com/th?id=OHR.GuwahatiDiwali_EN-US3454357880_UHD.jpg&pid=hp&w=3840&h=2160&rs=1&c=4","preview":"https://cn.bing.com/th?id=OHR.GuwahatiDiwali_EN-US3454357880_UHD.jpg&pid=hp&w=384&h=216&rs=1&c=4","large":"https://cn.bing.com/th?id=OHR.GuwahatiDiwali_EN-US3454357880_UHD.jpg&pid=hp&w=3840&h=2160&rs=1&c=4","medium":"https://cn.bing.com/th?id=OHR.GuwahatiDiwali_EN-US3454357880_UHD.jpg&w=1000","copyright":"Oil lamps arranged on a rangoli to celebrate Diwali in Guwahati, India (© Biju Boro/Getty Images)","date":"2022-10-25","title":"Lighting the world","copyrightlink":"/search?q=diwali+2022&form=hpcapt&filters=HpDate%3a%2220221024_0700%22"},{"url":"https://cn.bing.com/th?id=OHR.Knobbelzwaan_EN-US4809716001_UHD.jpg&pid=hp&w=3840&h=2160&rs=1&c=4","preview":"https://cn.bing.com/th?id=OHR.Knobbelzwaan_EN-US4809716001_UHD.jpg&pid=hp&w=384&h=216&rs=1&c=4","large":"https://cn.bing.com/th?id=OHR.Knobbelzwaan_EN-US4809716001_UHD.jpg&pid=hp&w=3840&h=2160&rs=1&c=4","medium":"https://cn.bing.com/th?id=OHR.Knobbelzwaan_EN-US4809716001_UHD.jpg&w=1000","copyright":"Mute swan in Valkenhorst Nature Reserve, near Valkenswaard, the Netherlands (© David Pattyn/Minden Pictures)","date":"2022-10-24","title":"An ugly duckling no more","copyrightlink":"/search?q=Mute+swan&form=hpcapt&filters=HpDate%3a%2220221023_0700%22"},{"url":"https://cn.bing.com/th?id=OHR.KarstMountains_EN-US4446699673_UHD.jpg&pid=hp&w=3840&h=2160&rs=1&c=4","preview":"https://cn.bing.com/th?id=OHR.KarstMountains_EN-US4446699673_UHD.jpg&pid=hp&w=384&h=216&rs=1&c=4","large":"https://cn.bing.com/th?id=OHR.KarstMountains_EN-US4446699673_UHD.jpg&pid=hp&w=3840&h=2160&rs=1&c=4","medium":"https://cn.bing.com/th?id=OHR.KarstMountains_EN-US4446699673_UHD.jpg&w=1000","copyright":"Karst mountains in Guilin and Lijiang River National Park, China (© Sean Pavone/Alamy)","date":"2022-10-23","title":"Misty mountain hop","copyrightlink":"/search?q=guilin+and+lijiang+river+national+park+karst+mountains+topography&form=hpcapt&filters=HpDate%3a%2220221022_0700%22"},{"url":"https://cn.bing.com/th?id=OHR.GeorgiaCypress_EN-US2966839861_UHD.jpg&pid=hp&w=3840&h=2160&rs=1&c=4","preview":"https://cn.bing.com/th?id=OHR.GeorgiaCypress_EN-US2966839861_UHD.jpg&pid=hp&w=384&h=216&rs=1&c=4","large":"https://cn.bing.com/th?id=OHR.GeorgiaCypress_EN-US2966839861_UHD.jpg&pid=hp&w=3840&h=2160&rs=1&c=4","medium":"https://cn.bing.com/th?id=OHR.GeorgiaCypress_EN-US2966839861_UHD.jpg&w=1000","copyright":"Cypress trees in autumn, Georgia (© Chris Moore/Tandem Stills + Motion)","date":"2022-10-22","title":"Leaf-peeping, Southern style","copyrightlink":"/search?q=Bald+cypress&form=hpcapt&filters=HpDate%3a%2220221021_0700%22"},{"url":"https://cn.bing.com/th?id=OHR.SlothDay_EN-US8418438094_UHD.jpg&pid=hp&w=3840&h=2160&rs=1&c=4","preview":"https://cn.bing.com/th?id=OHR.SlothDay_EN-US8418438094_UHD.jpg&pid=hp&w=384&h=216&rs=1&c=4","large":"https://cn.bing.com/th?id=OHR.SlothDay_EN-US8418438094_UHD.jpg&pid=hp&w=3840&h=2160&rs=1&c=4","medium":"https://cn.bing.com/th?id=OHR.SlothDay_EN-US8418438094_UHD.jpg&w=1000","copyright":"Hoffmann's two-toed sloth mother and young, Puerto Viejo de Talamanca, Costa Rica (© Suzi Eszterhas/Minden Pictures)","date":"2022-10-21","title":"Hangin' around","copyrightlink":"/search?q=Hoffmann%27s+two-toed+sloth&FORM=hpcapt&filters=HpDate%3a%2220221020_0700%22"},{"url":"https://cn.bing.com/th?id=OHR.WartburgCastle_EN-US8283353282_UHD.jpg&pid=hp&w=3840&h=2160&rs=1&c=4","preview":"https://cn.bing.com/th?id=OHR.WartburgCastle_EN-US8283353282_UHD.jpg&pid=hp&w=384&h=216&rs=1&c=4","large":"https://cn.bing.com/th?id=OHR.WartburgCastle_EN-US8283353282_UHD.jpg&pid=hp&w=3840&h=2160&rs=1&c=4","medium":"https://cn.bing.com/th?id=OHR.WartburgCastle_EN-US8283353282_UHD.jpg&w=1000","copyright":"Thuringian Forest in autumn with Wartburg Castle, Germany (© ezypix/Getty Images)","date":"2022-10-20","title":"'Wait, mountain—you shall bear my castle!'","copyrightlink":"/search?q=wartburg+castle+history+ludwig+der+springer&form=hpcapt&filters=HpDate%3a%2220221019_0700%22"},{"url":"https://cn.bing.com/th?id=OHR.GB25Anni_EN-US8198972228_UHD.jpg&pid=hp&w=3840&h=2160&rs=1&c=4","preview":"https://cn.bing.com/th?id=OHR.GB25Anni_EN-US8198972228_UHD.jpg&pid=hp&w=384&h=216&rs=1&c=4","large":"https://cn.bing.com/th?id=OHR.GB25Anni_EN-US8198972228_UHD.jpg&pid=hp&w=3840&h=2160&rs=1&c=4","medium":"https://cn.bing.com/th?id=OHR.GB25Anni_EN-US8198972228_UHD.jpg&w=1000","copyright":"Guggenheim Museum Bilbao, Spain (© Jeremy Horner/Getty Images)","date":"2022-10-19","title":"Night outside the museum","copyrightlink":"/search?q=guggenheim+museum+bilbao+established+date&form=hpcapt&filters=HpDate%3a%2220221018_0700%22"},{"url":"https://cn.bing.com/th?id=OHR.SwedenOwl_EN-US8107135630_UHD.jpg&pid=hp&w=3840&h=2160&rs=1&c=4","preview":"https://cn.bing.com/th?id=OHR.SwedenOwl_EN-US8107135630_UHD.jpg&pid=hp&w=384&h=216&rs=1&c=4","large":"https://cn.bing.com/th?id=OHR.SwedenOwl_EN-US8107135630_UHD.jpg&pid=hp&w=3840&h=2160&rs=1&c=4","medium":"https://cn.bing.com/th?id=OHR.SwedenOwl_EN-US8107135630_UHD.jpg&w=1000","copyright":"Long-eared owl in the Bohemian-Moravian Highlands of the Czech Republic (© Ondrej Prosicky/Alamy)","date":"2022-10-18","title":"Widespread and long-eared","copyrightlink":"/search?q=Long-eared+owl&form=hpcapt&filters=HpDate%3a%2220221017_0700%22"},{"url":"https://cn.bing.com/th?id=OHR.PrinceChristianSound_EN-US8033823843_UHD.jpg&pid=hp&w=3840&h=2160&rs=1&c=4","preview":"https://cn.bing.com/th?id=OHR.PrinceChristianSound_EN-US8033823843_UHD.jpg&pid=hp&w=384&h=216&rs=1&c=4","large":"https://cn.bing.com/th?id=OHR.PrinceChristianSound_EN-US8033823843_UHD.jpg&pid=hp&w=3840&h=2160&rs=1&c=4","medium":"https://cn.bing.com/th?id=OHR.PrinceChristianSound_EN-US8033823843_UHD.jpg&w=1000","copyright":"Prince Christian Sound in southern Greenland (© Posnov/Getty Images)","date":"2022-10-17","title":"Southern tip of a northern isle","copyrightlink":"/search?q=prince+christian+sound+greenland&form=hpcapt&filters=HpDate%3a%2220221016_0700%22"},{"url":"https://cn.bing.com/th?id=OHR.NaqsheRustam_EN-US7919143366_UHD.jpg&pid=hp&w=3840&h=2160&rs=1&c=4","preview":"https://cn.bing.com/th?id=OHR.NaqsheRustam_EN-US7919143366_UHD.jpg&pid=hp&w=384&h=216&rs=1&c=4","large":"https://cn.bing.com/th?id=OHR.NaqsheRustam_EN-US7919143366_UHD.jpg&pid=hp&w=3840&h=2160&rs=1&c=4","medium":"https://cn.bing.com/th?id=OHR.NaqsheRustam_EN-US7919143366_UHD.jpg&w=1000","copyright":"Naqsh-e Rostam archaeological site near Persepolis, Iran (© mshirani/Shutterstock)","date":"2022-10-16","title":"Final resting place of kings","copyrightlink":"/search?q=naqsh-e+rostam+iran&form=hpcapt&filters=HpDate%3a%2220221015_0700%22"},{"url":"https://cn.bing.com/th?id=OHR.RioArazas_EN-US7767502808_UHD.jpg&pid=hp&w=3840&h=2160&rs=1&c=4","preview":"https://cn.bing.com/th?id=OHR.RioArazas_EN-US7767502808_UHD.jpg&pid=hp&w=384&h=216&rs=1&c=4","large":"https://cn.bing.com/th?id=OHR.RioArazas_EN-US7767502808_UHD.jpg&pid=hp&w=3840&h=2160&rs=1&c=4","medium":"https://cn.bing.com/th?id=OHR.RioArazas_EN-US7767502808_UHD.jpg&w=1000","copyright":"Waterfall on the Río Arazas in Ordesa y Monte Perdido National Park, Pyrenees, Spain (© David Santiago Garcia/Cavan Images)","date":"2022-10-15","title":"Gateway to Iberia","copyrightlink":"/search?q=ordesa+y+monte+perdido+national+park+pyrenees+spain+history&form=hpcapt&filters=HpDate%3a%2220221014_0700%22"},{"url":"https://cn.bing.com/th?id=OHR.AlaskaMoose_EN-US7632880778_UHD.jpg&pid=hp&w=3840&h=2160&rs=1&c=4","preview":"https://cn.bing.com/th?id=OHR.AlaskaMoose_EN-US7632880778_UHD.jpg&pid=hp&w=384&h=216&rs=1&c=4","large":"https://cn.bing.com/th?id=OHR.AlaskaMoose_EN-US7632880778_UHD.jpg&pid=hp&w=3840&h=2160&rs=1&c=4","medium":"https://cn.bing.com/th?id=OHR.AlaskaMoose_EN-US7632880778_UHD.jpg&w=1000","copyright":"Bull and female moose in Denali National Park, Alaska (© Yva Momatiuk and John Eastcott/Minden Pictures)","date":"2022-10-14","title":"When being in a rut is OK","copyrightlink":"/search?q=Alces+alces+gigas&form=hpcapt&filters=HpDate%3a%2220221013_0700%22"},{"url":"https://cn.bing.com/th?id=OHR.AmmoniteGraveyard_EN-US7510840532_UHD.jpg&pid=hp&w=3840&h=2160&rs=1&c=4","preview":"https://cn.bing.com/th?id=OHR.AmmoniteGraveyard_EN-US7510840532_UHD.jpg&pid=hp&w=384&h=216&rs=1&c=4","large":"https://cn.bing.com/th?id=OHR.AmmoniteGraveyard_EN-US7510840532_UHD.jpg&pid=hp&w=3840&h=2160&rs=1&c=4","medium":"https://cn.bing.com/th?id=OHR.AmmoniteGraveyard_EN-US7510840532_UHD.jpg&w=1000","copyright":"Ammonite Pavement at Monmouth Beach, Jurassic Coast World Heritage Site, Dorset, England (© AWL Images/Danita Delimont)","date":"2022-10-13","title":"Stepping back in time","copyrightlink":"/search?q=jurassic+coast+dorset+england+history&form=hpcapt&filters=HpDate%3a%2220221012_0700%22"},{"url":"https://cn.bing.com/th?id=OHR.TortulaMoss_EN-US7128071079_UHD.jpg&pid=hp&w=3840&h=2160&rs=1&c=4","preview":"https://cn.bing.com/th?id=OHR.TortulaMoss_EN-US7128071079_UHD.jpg&pid=hp&w=384&h=216&rs=1&c=4","large":"https://cn.bing.com/th?id=OHR.TortulaMoss_EN-US7128071079_UHD.jpg&pid=hp&w=3840&h=2160&rs=1&c=4","medium":"https://cn.bing.com/th?id=OHR.TortulaMoss_EN-US7128071079_UHD.jpg&w=1000","copyright":"Wall screw-moss glistening with water droplets, Netherlands (© Arjan Troost/Minden Pictures)","date":"2022-10-12","title":"Magnified moss","copyrightlink":"/search?q=tortula+muralis&form=hpcapt&filters=HpDate%3a%2220221011_0700%22"},{"url":"https://cn.bing.com/th?id=OHR.SacredSmoke_EN-US7047459944_UHD.jpg&pid=hp&w=3840&h=2160&rs=1&c=4","preview":"https://cn.bing.com/th?id=OHR.SacredSmoke_EN-US7047459944_UHD.jpg&pid=hp&w=384&h=216&rs=1&c=4","large":"https://cn.bing.com/th?id=OHR.SacredSmoke_EN-US7047459944_UHD.jpg&pid=hp&w=3840&h=2160&rs=1&c=4","medium":"https://cn.bing.com/th?id=OHR.SacredSmoke_EN-US7047459944_UHD.jpg&w=1000","copyright":"The 'Circle of Sacred Smoke' sculpture by Junkyu Muto frames Devils Tower in Wyoming (© Nagel Photography/Shutterstock)","date":"2022-10-11","title":"'Circle of Sacred Smoke'","copyrightlink":"/search?q=indigenous+peoples+day&form=hpcapt&filters=HpDate%3a%2220221010_0700%22"},{"url":"https://cn.bing.com/th?id=OHR.ChukchiSea_EN-US6494940864_UHD.jpg&pid=hp&w=3840&h=2160&rs=1&c=4","preview":"https://cn.bing.com/th?id=OHR.ChukchiSea_EN-US6494940864_UHD.jpg&pid=hp&w=384&h=216&rs=1&c=4","large":"https://cn.bing.com/th?id=OHR.ChukchiSea_EN-US6494940864_UHD.jpg&pid=hp&w=3840&h=2160&rs=1&c=4","medium":"https://cn.bing.com/th?id=OHR.ChukchiSea_EN-US6494940864_UHD.jpg&w=1000","copyright":"Phytoplankton blooming in the Chukchi Sea off the coast of Alaska (© Norman Kuring/Kathryn Hansen/U.S. Geological Survey/NASA)","date":"2022-10-10","title":"What's blooming so brightly?","copyrightlink":"/search?q=earth+science+week&form=hpcapt&filters=HpDate%3a%2220221009_0700%22"},{"url":"https://cn.bing.com/th?id=OHR.GlassOctopus_EN-US6394802515_UHD.jpg&pid=hp&w=3840&h=2160&rs=1&c=4","preview":"https://cn.bing.com/th?id=OHR.GlassOctopus_EN-US6394802515_UHD.jpg&pid=hp&w=384&h=216&rs=1&c=4","large":"https://cn.bing.com/th?id=OHR.GlassOctopus_EN-US6394802515_UHD.jpg&pid=hp&w=3840&h=2160&rs=1&c=4","medium":"https://cn.bing.com/th?id=OHR.GlassOctopus_EN-US6394802515_UHD.jpg&w=1000","copyright":"Glass octopus in the Atlantic Ocean off Cabo Verde (© Solvin Zankl/Minden Pictures)","date":"2022-10-09","title":"See-through cephalopod","copyrightlink":"/search?q=world+octopus+day&form=hpcapt&filters=HpDate%3a%2220221008_0700%22"},{"url":"https://cn.bing.com/th?id=OHR.OberbaumBridge_EN-US6324390642_UHD.jpg&pid=hp&w=3840&h=2160&rs=1&c=4","preview":"https://cn.bing.com/th?id=OHR.OberbaumBridge_EN-US6324390642_UHD.jpg&pid=hp&w=384&h=216&rs=1&c=4","large":"https://cn.bing.com/th?id=OHR.OberbaumBridge_EN-US6324390642_UHD.jpg&pid=hp&w=3840&h=2160&rs=1&c=4","medium":"https://cn.bing.com/th?id=OHR.OberbaumBridge_EN-US6324390642_UHD.jpg&w=1000","copyright":"Designs projected on the Oberbaum Bridge during the yearly Festival of Lights in Berlin, Germany (© John MacDougall/AFP via Getty Images)","date":"2022-10-08","title":"An old bridge in a new light","copyrightlink":"/search?q=Festival+of+Lights+in+Berlin&FORM=hpcapt&filters=HpDate%3a%2220221007_0700%22"},{"url":"https://cn.bing.com/th?id=OHR.BayofBiscay_EN-US8933430968_UHD.jpg&pid=hp&w=3840&h=2160&rs=1&c=4","preview":"https://cn.bing.com/th?id=OHR.BayofBiscay_EN-US8933430968_UHD.jpg&pid=hp&w=384&h=216&rs=1&c=4","large":"https://cn.bing.com/th?id=OHR.BayofBiscay_EN-US8933430968_UHD.jpg&pid=hp&w=3840&h=2160&rs=1&c=4","medium":"https://cn.bing.com/th?id=OHR.BayofBiscay_EN-US8933430968_UHD.jpg&w=1000","copyright":"Basque Coast Geopark in the Bay of Biscay near Bilbao, Spain (© Olimpio Fantuz/eStock Photo)","date":"2022-10-07","title":"Dragon tails trail to the sea","copyrightlink":"/search?q=basque+coast+geopark+diversity&form=hpcapt&filters=HpDate%3a%2220221006_0700%22"},{"url":"https://cn.bing.com/th?id=OHR.FlamingoTeacher_EN-US8819896781_UHD.jpg&pid=hp&w=3840&h=2160&rs=1&c=4","preview":"https://cn.bing.com/th?id=OHR.FlamingoTeacher_EN-US8819896781_UHD.jpg&pid=hp&w=384&h=216&rs=1&c=4","large":"https://cn.bing.com/th?id=OHR.FlamingoTeacher_EN-US8819896781_UHD.jpg&pid=hp&w=3840&h=2160&rs=1&c=4","medium":"https://cn.bing.com/th?id=OHR.FlamingoTeacher_EN-US8819896781_UHD.jpg&w=1000","copyright":"Caribbean flamingos, Ría Lagartos Biosphere Reserve, Yucatán Peninsula, Mexico (© Claudio Contreras/Minden Pictures)","date":"2022-10-06","title":"Single file, now!","copyrightlink":"/search?q=world+teachers+day&form=hpcapt&filters=HpDate%3a%2220221005_0700%22"},{"url":"https://cn.bing.com/th?id=OHR.CosmicCliffs_EN-US8727581889_UHD.jpg&pid=hp&w=3840&h=2160&rs=1&c=4","preview":"https://cn.bing.com/th?id=OHR.CosmicCliffs_EN-US8727581889_UHD.jpg&pid=hp&w=384&h=216&rs=1&c=4","large":"https://cn.bing.com/th?id=OHR.CosmicCliffs_EN-US8727581889_UHD.jpg&pid=hp&w=3840&h=2160&rs=1&c=4","medium":"https://cn.bing.com/th?id=OHR.CosmicCliffs_EN-US8727581889_UHD.jpg&w=1000","copyright":"Cosmic Cliffs in the Carina Nebula (© NASA, ESA, CSA, and STScI)","date":"2022-10-05","title":"Golden cliffs of deep space","copyrightlink":"/search?q=world+space+week&form=hpcapt&filters=HpDate%3a%2220221004_0700%22"},{"url":"https://cn.bing.com/th?id=OHR.Porthuis_EN-US8462686696_UHD.jpg&pid=hp&w=3840&h=2160&rs=1&c=4","preview":"https://cn.bing.com/th?id=OHR.Porthuis_EN-US8462686696_UHD.jpg&pid=hp&w=384&h=216&rs=1&c=4","large":"https://cn.bing.com/th?id=OHR.Porthuis_EN-US8462686696_UHD.jpg&pid=hp&w=3840&h=2160&rs=1&c=4","medium":"https://cn.bing.com/th?id=OHR.Porthuis_EN-US8462686696_UHD.jpg&w=1000","copyright":"The Port House, designed by Zaha Hadid Architects, Antwerp, Belgium (© Dmitry Rukhlenko/Alamy)","date":"2022-10-04","title":"A future built on the past","copyrightlink":"/search?q=architecture&form=hpcapt&filters=HpDate%3a%2220221003_0700%22"},{"url":"https://cn.bing.com/th?id=OHR.LotsOBalloons_EN-US8236203600_UHD.jpg&pid=hp&w=3840&h=2160&rs=1&c=4","preview":"https://cn.bing.com/th?id=OHR.LotsOBalloons_EN-US8236203600_UHD.jpg&pid=hp&w=384&h=216&rs=1&c=4","large":"https://cn.bing.com/th?id=OHR.LotsOBalloons_EN-US8236203600_UHD.jpg&pid=hp&w=3840&h=2160&rs=1&c=4","medium":"https://cn.bing.com/th?id=OHR.LotsOBalloons_EN-US8236203600_UHD.jpg&w=1000","copyright":"Hot air balloons at the Albuquerque International Balloon Fiesta in Albuquerque, New Mexico (© gmeland/Shutterstock)","date":"2022-10-03","title":"The oldest way to fly","copyrightlink":"/search?q=albuquerque+international+balloon+fiesta+history&FORM=hpcapt&filters=HpDate%3a%2220221002_0700%22"},{"url":"https://cn.bing.com/th?id=OHR.BridalVeilFalls_EN-US8055892423_UHD.jpg&pid=hp&w=3840&h=2160&rs=1&c=4","preview":"https://cn.bing.com/th?id=OHR.BridalVeilFalls_EN-US8055892423_UHD.jpg&pid=hp&w=384&h=216&rs=1&c=4","large":"https://cn.bing.com/th?id=OHR.BridalVeilFalls_EN-US8055892423_UHD.jpg&pid=hp&w=3840&h=2160&rs=1&c=4","medium":"https://cn.bing.com/th?id=OHR.BridalVeilFalls_EN-US8055892423_UHD.jpg&w=1000","copyright":"Bridalveil Fall, Yosemite National Park, California (© Jeff Foott/Minden Pictures)","date":"2022-10-02","title":"Spirit of the Puffing Wind","copyrightlink":"/search?q=yosemite+national+park+history&form=hpcapt&filters=HpDate%3a%2220221001_0700%22"},{"url":"https://cn.bing.com/th?id=OHR.EubalaenaAustralis_EN-US7949014397_UHD.jpg&pid=hp&w=3840&h=2160&rs=1&c=4","preview":"https://cn.bing.com/th?id=OHR.EubalaenaAustralis_EN-US7949014397_UHD.jpg&pid=hp&w=384&h=216&rs=1&c=4","large":"https://cn.bing.com/th?id=OHR.EubalaenaAustralis_EN-US7949014397_UHD.jpg&pid=hp&w=3840&h=2160&rs=1&c=4","medium":"https://cn.bing.com/th?id=OHR.EubalaenaAustralis_EN-US7949014397_UHD.jpg&w=1000","copyright":"Southern right whale diving in the Golfo Nuevo near the Valdes Peninsula, Argentina (© Gabriel Rojo/Minden Pictures)","date":"2022-10-01","title":"Giants of the Southern Ocean","copyrightlink":"/search?q=Southern+right+whale&form=hpcapt&filters=HpDate%3a%2220220930_0700%22"}]