[{"url":"https://cn.bing.com/th?id=OHR.MorroJable_EN-US1772722431_UHD.jpg&pid=hp&w=3840&h=2160&rs=1&c=4","preview":"https://cn.bing.com/th?id=OHR.MorroJable_EN-US1772722431_UHD.jpg&pid=hp&w=384&h=216&rs=1&c=4","large":"https://cn.bing.com/th?id=OHR.MorroJable_EN-US1772722431_UHD.jpg&pid=hp&w=3840&h=2160&rs=1&c=4","medium":"https://cn.bing.com/th?id=OHR.MorroJable_EN-US1772722431_UHD.jpg&w=1000","copyright":"Morro Jable and Playa del Matorral, Fuerteventura, Canary Islands, Spain (© Gavin Hellier/Getty Images)","date":"2023-05-16","title":"Aglow in the Atlantic","copyrightlink":"/search?q=canary+islands&form=hpcapt&filters=HpDate%3a%2220230515_0700%22"},{"url":"https://cn.bing.com/th?id=OHR.OdocoileusVirginianus_EN-US1668598337_UHD.jpg&pid=hp&w=3840&h=2160&rs=1&c=4","preview":"https://cn.bing.com/th?id=OHR.OdocoileusVirginianus_EN-US1668598337_UHD.jpg&pid=hp&w=384&h=216&rs=1&c=4","large":"https://cn.bing.com/th?id=OHR.OdocoileusVirginianus_EN-US1668598337_UHD.jpg&pid=hp&w=3840&h=2160&rs=1&c=4","medium":"https://cn.bing.com/th?id=OHR.OdocoileusVirginianus_EN-US1668598337_UHD.jpg&w=1000","copyright":"White-tailed deer doe and newborn fawn, Montana (© Donald M. Jones/Minden Pictures)","date":"2023-05-15","title":"Happy Mother's Day!","copyrightlink":"/search?q=mother%27s+day&form=hpcapt&filters=HpDate%3a%2220230514_0700%22"},{"url":"https://cn.bing.com/th?id=OHR.SonnyBonoPelicans_EN-US1524460012_UHD.jpg&pid=hp&w=3840&h=2160&rs=1&c=4","preview":"https://cn.bing.com/th?id=OHR.SonnyBonoPelicans_EN-US1524460012_UHD.jpg&pid=hp&w=384&h=216&rs=1&c=4","large":"https://cn.bing.com/th?id=OHR.SonnyBonoPelicans_EN-US1524460012_UHD.jpg&pid=hp&w=3840&h=2160&rs=1&c=4","medium":"https://cn.bing.com/th?id=OHR.SonnyBonoPelicans_EN-US1524460012_UHD.jpg&w=1000","copyright":"Pelicans at Sonny Bono Salton Sea National Wildlife Refuge, California (© David McNew/Getty Images)","date":"2023-05-14","title":"'Tis the season for travel","copyrightlink":"/search?q=bird+migration&form=hpcapt&filters=HpDate%3a%2220230513_0700%22"},{"url":"https://cn.bing.com/th?id=OHR.WildLupine_EN-US1382733552_UHD.jpg&pid=hp&w=3840&h=2160&rs=1&c=4","preview":"https://cn.bing.com/th?id=OHR.WildLupine_EN-US1382733552_UHD.jpg&pid=hp&w=384&h=216&rs=1&c=4","large":"https://cn.bing.com/th?id=OHR.WildLupine_EN-US1382733552_UHD.jpg&pid=hp&w=3840&h=2160&rs=1&c=4","medium":"https://cn.bing.com/th?id=OHR.WildLupine_EN-US1382733552_UHD.jpg&w=1000","copyright":"Wild lupines in bloom (© silverjohn/Getty Images Plus)","date":"2023-05-13","title":"A butterfly's best friend","copyrightlink":"/search?q=Wild+lupine&form=hpcapt&filters=HpDate%3a%2220230512_0700%22"},{"url":"https://cn.bing.com/th?id=OHR.FootballField_EN-US1266832046_UHD.jpg&pid=hp&w=3840&h=2160&rs=1&c=4","preview":"https://cn.bing.com/th?id=OHR.FootballField_EN-US1266832046_UHD.jpg&pid=hp&w=384&h=216&rs=1&c=4","large":"https://cn.bing.com/th?id=OHR.FootballField_EN-US1266832046_UHD.jpg&pid=hp&w=3840&h=2160&rs=1&c=4","medium":"https://cn.bing.com/th?id=OHR.FootballField_EN-US1266832046_UHD.jpg&w=1000","copyright":"Henningsvær Stadion, Norway (© Morten Falch Sortland/Getty Images)","date":"2023-05-12","title":"Pitch perfect","copyrightlink":"/search?q=Henningsv%c3%a6r&form=hpcapt&filters=HpDate%3a%2220230511_0700%22"},{"url":"https://cn.bing.com/th?id=OHR.CordouanLighthouse_EN-US1179388866_UHD.jpg&pid=hp&w=3840&h=2160&rs=1&c=4","preview":"https://cn.bing.com/th?id=OHR.CordouanLighthouse_EN-US1179388866_UHD.jpg&pid=hp&w=384&h=216&rs=1&c=4","large":"https://cn.bing.com/th?id=OHR.CordouanLighthouse_EN-US1179388866_UHD.jpg&pid=hp&w=3840&h=2160&rs=1&c=4","medium":"https://cn.bing.com/th?id=OHR.CordouanLighthouse_EN-US1179388866_UHD.jpg&w=1000","copyright":"Cordouan Lighthouse, Royan, Charente, France (© FRTimelapse/Getty Images)","date":"2023-05-11","title":"King of lighthouses","copyrightlink":"/search?q=Cordouan+Lighthouse&form=hpcapt&filters=HpDate%3a%2220230510_0700%22"},{"url":"https://cn.bing.com/th?id=OHR.MountCetatea_EN-US0862689024_UHD.jpg&pid=hp&w=3840&h=2160&rs=1&c=4","preview":"https://cn.bing.com/th?id=OHR.MountCetatea_EN-US0862689024_UHD.jpg&pid=hp&w=384&h=216&rs=1&c=4","large":"https://cn.bing.com/th?id=OHR.MountCetatea_EN-US0862689024_UHD.jpg&pid=hp&w=3840&h=2160&rs=1&c=4","medium":"https://cn.bing.com/th?id=OHR.MountCetatea_EN-US0862689024_UHD.jpg&w=1000","copyright":"Poenari Castle on Mount Cetatea, Făgăraș Mountains, Romania (© porojnicu/Getty Images)","date":"2023-05-10","title":"A castle fit for a count","copyrightlink":"/search?q=Poenari+Castle&form=hpcapt&filters=HpDate%3a%2220230509_0700%22"},{"url":"https://cn.bing.com/th?id=OHR.TheChaps_EN-US0810025310_UHD.jpg&pid=hp&w=3840&h=2160&rs=1&c=4","preview":"https://cn.bing.com/th?id=OHR.TheChaps_EN-US0810025310_UHD.jpg&pid=hp&w=384&h=216&rs=1&c=4","large":"https://cn.bing.com/th?id=OHR.TheChaps_EN-US0810025310_UHD.jpg&pid=hp&w=3840&h=2160&rs=1&c=4","medium":"https://cn.bing.com/th?id=OHR.TheChaps_EN-US0810025310_UHD.jpg&w=1000","copyright":"Delicate Arch, Arches National Park, Utah (© Mark Brodkin Photography/Getty Images)","date":"2023-05-09","title":"Delicate but enduring","copyrightlink":"/search?q=Delicate+Arch+Utah&form=hpcapt&filters=HpDate%3a%2220230508_0700%22"},{"url":"https://cn.bing.com/th?id=OHR.SealLaughing_EN-US0742497806_UHD.jpg&pid=hp&w=3840&h=2160&rs=1&c=4","preview":"https://cn.bing.com/th?id=OHR.SealLaughing_EN-US0742497806_UHD.jpg&pid=hp&w=384&h=216&rs=1&c=4","large":"https://cn.bing.com/th?id=OHR.SealLaughing_EN-US0742497806_UHD.jpg&pid=hp&w=3840&h=2160&rs=1&c=4","medium":"https://cn.bing.com/th?id=OHR.SealLaughing_EN-US0742497806_UHD.jpg&w=1000","copyright":"Gray seal pup, Lundy Island, England (© Henley Spiers/Minden Pictures)","date":"2023-05-08","title":"Happy World Laughter Day!","copyrightlink":"/search?q=gray+seal+(Halichoerus+grypus)&form=hpcapt&filters=HpDate%3a%2220230507_0700%22"},{"url":"https://cn.bing.com/th?id=OHR.HwangmaesanAzaleas_EN-US0649441292_UHD.jpg&pid=hp&w=3840&h=2160&rs=1&c=4","preview":"https://cn.bing.com/th?id=OHR.HwangmaesanAzaleas_EN-US0649441292_UHD.jpg&pid=hp&w=384&h=216&rs=1&c=4","large":"https://cn.bing.com/th?id=OHR.HwangmaesanAzaleas_EN-US0649441292_UHD.jpg&pid=hp&w=3840&h=2160&rs=1&c=4","medium":"https://cn.bing.com/th?id=OHR.HwangmaesanAzaleas_EN-US0649441292_UHD.jpg&w=1000","copyright":"Royal azaleas in bloom on Hwangmaesan Mountain, South Korea (© Stock for you/Shutterstock)","date":"2023-05-07","title":"The purple peaks of Hwangmaesan","copyrightlink":"/search?q=hwangmaesan+mountain&form=hpcapt&filters=HpDate%3a%2220230506_0700%22"},{"url":"https://cn.bing.com/th?id=OHR.Popocatepetl_EN-US0582960818_UHD.jpg&pid=hp&w=3840&h=2160&rs=1&c=4","preview":"https://cn.bing.com/th?id=OHR.Popocatepetl_EN-US0582960818_UHD.jpg&pid=hp&w=384&h=216&rs=1&c=4","large":"https://cn.bing.com/th?id=OHR.Popocatepetl_EN-US0582960818_UHD.jpg&pid=hp&w=3840&h=2160&rs=1&c=4","medium":"https://cn.bing.com/th?id=OHR.Popocatepetl_EN-US0582960818_UHD.jpg&w=1000","copyright":"Church of Nuestra Señora de los Remedios and Popocatépetl, Puebla, Mexico (© Radius Images/Shutterstock)","date":"2023-05-06","title":"Celebrating Cinco de Mayo","copyrightlink":"/search?q=Church+of+Nuestra+Senora+de+los+Remedios+cholula&form=hpcapt&filters=HpDate%3a%2220230505_0700%22"},{"url":"https://cn.bing.com/th?id=OHR.RebelBase_EN-US9162228478_UHD.jpg&pid=hp&w=3840&h=2160&rs=1&c=4","preview":"https://cn.bing.com/th?id=OHR.RebelBase_EN-US9162228478_UHD.jpg&pid=hp&w=384&h=216&rs=1&c=4","large":"https://cn.bing.com/th?id=OHR.RebelBase_EN-US9162228478_UHD.jpg&pid=hp&w=3840&h=2160&rs=1&c=4","medium":"https://cn.bing.com/th?id=OHR.RebelBase_EN-US9162228478_UHD.jpg&w=1000","copyright":"Mayan ruins in Tikal, Guatemala (© THP Creative/Getty Images)","date":"2023-05-05","title":"May the Fourth be with you","copyrightlink":"/search?q=Tikal+world+heritage+site&form=hpcapt&filters=HpDate%3a%2220230504_0700%22"},{"url":"https://cn.bing.com/th?id=OHR.ThreeWildebeest_EN-US9446203427_UHD.jpg&pid=hp&w=3840&h=2160&rs=1&c=4","preview":"https://cn.bing.com/th?id=OHR.ThreeWildebeest_EN-US9446203427_UHD.jpg&pid=hp&w=384&h=216&rs=1&c=4","large":"https://cn.bing.com/th?id=OHR.ThreeWildebeest_EN-US9446203427_UHD.jpg&pid=hp&w=3840&h=2160&rs=1&c=4","medium":"https://cn.bing.com/th?id=OHR.ThreeWildebeest_EN-US9446203427_UHD.jpg&w=1000","copyright":"Wildebeests in the Maasai Mara National Reserve, Kenya (© Matt Polski/Getty Images)","date":"2023-05-04","title":"The animal kingdom's great migration","copyrightlink":"/search?q=Wildebeests&form=hpcapt&filters=HpDate%3a%2220230503_0700%22"},{"url":"https://cn.bing.com/th?id=OHR.KlostersSerneus_EN-US9360254697_UHD.jpg&pid=hp&w=3840&h=2160&rs=1&c=4","preview":"https://cn.bing.com/th?id=OHR.KlostersSerneus_EN-US9360254697_UHD.jpg&pid=hp&w=384&h=216&rs=1&c=4","large":"https://cn.bing.com/th?id=OHR.KlostersSerneus_EN-US9360254697_UHD.jpg&pid=hp&w=3840&h=2160&rs=1&c=4","medium":"https://cn.bing.com/th?id=OHR.KlostersSerneus_EN-US9360254697_UHD.jpg&w=1000","copyright":"Jöriseen lakes in the Silvretta Alps, Switzerland (© Florin Baumann/Getty Images)","date":"2023-05-03","title":"The height of Alpine beauty","copyrightlink":"/search?q=J%c3%b6riseen+lakes&form=hpcapt&filters=HpDate%3a%2220230502_0700%22"},{"url":"https://cn.bing.com/th?id=OHR.KoreanBell_EN-US9211069806_UHD.jpg&pid=hp&w=3840&h=2160&rs=1&c=4","preview":"https://cn.bing.com/th?id=OHR.KoreanBell_EN-US9211069806_UHD.jpg&pid=hp&w=384&h=216&rs=1&c=4","large":"https://cn.bing.com/th?id=OHR.KoreanBell_EN-US9211069806_UHD.jpg&pid=hp&w=3840&h=2160&rs=1&c=4","medium":"https://cn.bing.com/th?id=OHR.KoreanBell_EN-US9211069806_UHD.jpg&w=1000","copyright":"Korean Bell of Friendship, Los Angeles (© Carlos Marin/Getty Images)","date":"2023-05-02","title":"Asian American and Pacific Islander Heritage Month","copyrightlink":"/search?q=korean+bell+of+friendship&form=hpcapt&filters=HpDate%3a%2220230501_0700%22"},{"url":"https://cn.bing.com/th?id=OHR.ExteriorPreservationHall_EN-US9095698933_UHD.jpg&pid=hp&w=3840&h=2160&rs=1&c=4","preview":"https://cn.bing.com/th?id=OHR.ExteriorPreservationHall_EN-US9095698933_UHD.jpg&pid=hp&w=384&h=216&rs=1&c=4","large":"https://cn.bing.com/th?id=OHR.ExteriorPreservationHall_EN-US9095698933_UHD.jpg&pid=hp&w=3840&h=2160&rs=1&c=4","medium":"https://cn.bing.com/th?id=OHR.ExteriorPreservationHall_EN-US9095698933_UHD.jpg&w=1000","copyright":"Preservation Hall, New Orleans, Louisiana (© Cosmo Condina North America/Alamy)","date":"2023-05-01","title":"A day of swing and celebration","copyrightlink":"/search?q=preservation+hall&form=hpcapt&filters=HpDate%3a%2220230430_0700%22"}]